Metadata-Version: 2.1
Name: openshield
Version: 0.1.0
Summary: OpenShield, a fast and easy-to-use CLI antivirus.
Home-page: https://github.com/jaedsonpys/openshield
Author: Jaedson Silva
Author-email: jaedson.dev@proton.me
License: MIT
Keywords: antivirus,malware,scanner,cli
Classifier: License :: OSI Approved :: MIT License
Classifier: Development Status :: 5 - Production/Stable
Classifier: Natural Language :: English
Classifier: Operating System :: OS Independent
Classifier: Programming Language :: Python :: 3
Classifier: Topic :: Security
Requires-Python: >=3.7
License-File: LICENSE
